chastack_utiles_flask/__init__.py
chastack_utiles_flask/imagenes.py
chastack_utiles_flask/ruteo.py
chastack_utiles_flask/texto.py
chastack_utiles_flask-0.1.4.dist-info/LICENSE
chastack_utiles_flask-0.1.4.dist-info/METADATA
chastack_utiles_flask-0.1.4.dist-info/WHEEL
chastack_utiles_flask-0.1.4.dist-info/top_level.txt
chastack_utiles_flask-0.1.4.dist-info/RECORD
